simpleDicomViewer/__init__.py
simpleDicomViewer/dicomViewer.py
simpledicomviewer-2.0.4.dist-info/METADATA
simpledicomviewer-2.0.4.dist-info/WHEEL
simpledicomviewer-2.0.4.dist-info/licenses/LICENSE
simpledicomviewer-2.0.4.dist-info/RECORD
