Metadata-Version: 2.4
Name: simpleDicomViewer
Version: 2.0.4
Summary: A package to simplify visualizing DICOM data, including images and segmentations (RTSTRUCT and SEG) via Jupyter/Python.
Project-URL: Homepage, https://github.com/kirbyju/simpleDicomViewer
Project-URL: Bug Tracker, https://github.com/kirbyju/simpleDicomViewer/issues
Author-email: Justin Kirby <justin.kirby@nih.gov>
License-File: LICENSE
Classifier: License :: OSI Approved :: Apache Software License
Classifier: Operating System :: OS Independent
Classifier: Programming Language :: Python :: 3
Requires-Python: >=3.9
Requires-Dist: ipython
Requires-Dist: ipywidgets
Requires-Dist: matplotlib
Requires-Dist: numpy
Requires-Dist: pydicom
Requires-Dist: rt-utils
